src/MCMC2ndGenTDI/MCMC2ndGen.py
src/MCMC2ndGenTDI/TDI_functions.py
src/MCMC2ndGenTDI/delay_time_dependence.py
src/MCMC2ndGenTDI/delay_time_dependence_Keplerian.py
src/MCMC2ndGenTDI/filter_functions.py
src/MCMC2ndGenTDI/mcmc_functions.py
src/MCMC2ndGenTDI/mcmc_functions_Keplerian.py
src/MCMC2ndGenTDI/settings.py
mcmc2ndgen-0.0.1.dist-info/METADATA
mcmc2ndgen-0.0.1.dist-info/WHEEL
mcmc2ndgen-0.0.1.dist-info/licenses/LICENSE
mcmc2ndgen-0.0.1.dist-info/RECORD
