Metadata-Version: 2.1
Name: MCMC2ndGen
Version: 0.0.1
Summary: An MCMC sampler for the time-varying LISA spacecraft separations used in TDI.
Project-URL: Homepage, https://github.com/JessicaPage/MCMC2ndGen
Author-email: Jessica Page <jp0089@uah.edu>
License-File: LICENSE
Classifier: License :: OSI Approved :: MIT License
Classifier: Operating System :: OS Independent
Classifier: Programming Language :: Python :: 3
Requires-Python: >=3.7
